odoo/addons/purchase_product_template_tags/README.rst
odoo/addons/purchase_product_template_tags/__init__.py
odoo/addons/purchase_product_template_tags/__manifest__.py
odoo/addons/purchase_product_template_tags/i18n/hr.po
odoo/addons/purchase_product_template_tags/i18n/it.po
odoo/addons/purchase_product_template_tags/i18n/purchase_product_template_tags.pot
odoo/addons/purchase_product_template_tags/readme/CONTRIBUTORS.md
odoo/addons/purchase_product_template_tags/readme/DESCRIPTION.md
odoo/addons/purchase_product_template_tags/static/description/icon.png
odoo/addons/purchase_product_template_tags/static/description/index.html
odoo/addons/purchase_product_template_tags/views/product_template_tag.xml
odoo_addon_purchase_product_template_tags-18.0.1.0.0.4.dist-info/METADATA
odoo_addon_purchase_product_template_tags-18.0.1.0.0.4.dist-info/WHEEL
odoo_addon_purchase_product_template_tags-18.0.1.0.0.4.dist-info/top_level.txt
odoo_addon_purchase_product_template_tags-18.0.1.0.0.4.dist-info/RECORD
